chauffeur/__init__.py
chauffeur/filters.py
chauffeur/formats.py
chauffeur/grammar.py
chauffeur/query.py
chauffeur/settings.py
chauffeur_pass-0.0.1.dist-info/LICENSE
chauffeur_pass-0.0.1.dist-info/METADATA
chauffeur_pass-0.0.1.dist-info/WHEEL
chauffeur_pass-0.0.1.dist-info/top_level.txt
chauffeur_pass-0.0.1.dist-info/RECORD
