Metadata-Version: 2.1
Name: chauffeur-pass
Version: 0.0.1
Summary: Python API for making OSM queries via Overpass
Home-page: https://github.com/rjpolackwich/chauffeur
Author: Jamison Polackwich
Author-email: rjpolackwich@gmail.com
License: MIT
Platform: UNKNOWN
Classifier: Programming Language :: Python :: 3
Classifier: License :: OSI Approved :: MIT License
Requires-Python: >3.7
License-File: LICENSE
Requires-Dist: python-dateutil
Requires-Dist: requests
